{"frame_0":{"version":"3.4.0","objects":[{"type":"image","version":"3.4.0","originX":"center","originY":"center","left":367.875,"top":154.8733799454,"width":65,"height":65,"fill":"#ff0000","stroke":null,"strokeWidth":0,"strokeDashArray":null,"strokeLineCap":"butt","strokeDashOffset":0,"strokeLineJoin":"miter","strokeMiterLimit":4,"scaleX":5.8615384615,"scaleY":4.6923575401,"angle":0,"flipX":false,"flipY":false,"opacity":1,"shadow":null,"visible":true,"clipTo":null,"backgroundColor":"","fillRule":"nonzero","paintFirst":"fill","globalCompositeOperation":"source-over","transformMatrix":null,"skewX":0,"skewY":0,"crossOrigin":"anonymous","cropX":0,"cropY":0,"objectCaching":true,"itemId":1586877425326,"selectable":true,"lockMovementX":false,"lockMovementY":false,"lockScalingX":false,"lockScalingY":false,"lockRotation":false,"evented":true,"absolutePositioned":false,"perPixelTargetFind":false,"centeredScaling":false,"src":"http://localhost/wordpress/wp-content/uploads/nbdesigner/temp/2020/04/14/1586877424ab49ef78.png","filters":[]},{"type":"group","version":"3.4.0","originX":"left","originY":"top","left":183.656,"top":251.5905,"width":677.2,"height":81.7,"fill":"#272c33","stroke":null,"strokeWidth":0,"strokeDashArray":null,"strokeLineCap":"butt","strokeDashOffset":0,"strokeLineJoin":"miter","strokeMiterLimit":10,"scaleX":0.54,"scaleY":0.57,"angle":0,"flipX":false,"flipY":false,"opacity":1,"shadow":null,"visible":true,"clipTo":null,"backgroundColor":"","fillRule":"nonzero","paintFirst":"fill","globalCompositeOperation":"source-over","transformMatrix":null,"skewX":0,"skewY":0,"objectCaching":true,"itemId":1529285875912,"selectable":true,"lockMovementX":false,"lockMovementY":false,"lockScalingX":false,"lockScalingY":false,"lockRotation":false,"evented":true,"absolutePositioned":false,"perPixelTargetFind":false,"centeredScaling":false,"objects":[{"type":"path","version":"3.4.0","originX":"left","originY":"top","left":-22.6,"top":-27.85,"width":45.6,"height":40,"fill":"#404762","stroke":null,"strokeWidth":1,"strokeDashArray":null,"strokeLineCap":"butt","strokeDashOffset":0,"strokeLineJoin":"miter","strokeMiterLimit":10,"scaleX":1,"scaleY":1,"angle":0,"flipX":false,"flipY":false,"opacity":1,"shadow":null,"visible":true,"clipTo":null,"backgroundColor":"","fillRule":"nonzero","paintFirst":"fill","globalCompositeOperation":"source-over","transformMatrix":null,"skewX":0,"skewY":0,"objectCaching":true,"selectable":true,"lockMovementX":false,"lockMovementY":false,"lockScalingX":false,"lockScalingY":false,"lockRotation":false,"evented":true,"absolutePositioned":false,"perPixelTargetFind":false,"centeredScaling":false,"path":[["M",-104.9,1201.7],["c",-5,0,-9.3,3.2,-11,7.6],["c",-1.7,-4.4,-6,-7.6,-11,-7.6],["c",-6.5,0,-11.8,5.3,-11.8,11.8],["c",0,12.7,22.8,28.2,22.8,28.2],["s",22.7,-15.6,22.8,-28.2],["C",-93.1,1207,-98.4,1201.7,-104.9,1201.7],["z"]]}]},{"type":"i-text","version":"3.4.0","originX":"left","originY":"top","left":269.316,"top":255.6305,"width":52.9399963379,"height":22.6,"fill":"#404762","stroke":null,"strokeWidth":1,"strokeDashArray":null,"strokeLineCap":"butt","strokeDashOffset":0,"strokeLineJoin":"miter","strokeMiterLimit":10,"scaleX":1.32,"scaleY":1.32,"angle":0,"flipX":false,"flipY":false,"opacity":1,"shadow":null,"visible":true,"clipTo":null,"backgroundColor":"","fillRule":"nonzero","paintFirst":"fill","globalCompositeOperation":"source-over","transformMatrix":null,"skewX":0,"skewY":0,"text":"ALEX","fontSize":20,"fontWeight":"normal","fontFamily":"Josefin Sans","fontStyle":"normal","lineHeight":1.16,"underline":false,"overline":false,"linethrough":false,"textAlign":"left","textBackgroundColor":"","charSpacing":0,"objectCaching":false,"itemId":1529285876739,"selectable":true,"editable":true,"lockMovementX":false,"lockMovementY":false,"lockScalingX":false,"lockScalingY":false,"lockRotation":true,"evented":true,"absolutePositioned":false,"perPixelTargetFind":false,"centeredScaling":false,"styles":{}},{"type":"i-text","version":"3.4.0","originX":"left","originY":"top","left":395.406,"top":255.6305,"width":52.8600006104,"height":22.6,"fill":"#404762","stroke":null,"strokeWidth":1,"strokeDashArray":null,"strokeLineCap":"butt","strokeDashOffset":0,"strokeLineJoin":"miter","strokeMiterLimit":10,"scaleX":1.32,"scaleY":1.32,"angle":0,"flipX":false,"flipY":false,"opacity":1,"shadow":null,"visible":true,"clipTo":null,"backgroundColor":"","fillRule":"nonzero","paintFirst":"fill","globalCompositeOperation":"source-over","transformMatrix":null,"skewX":0,"skewY":0,"text":"SARA","fontSize":20,"fontWeight":"normal","fontFamily":"Josefin Sans","fontStyle":"normal","lineHeight":1.16,"underline":false,"overline":false,"linethrough":false,"textAlign":"left","textBackgroundColor":"","charSpacing":0,"objectCaching":false,"itemId":1529285877187,"selectable":true,"editable":true,"lockMovementX":false,"lockMovementY":false,"lockScalingX":false,"lockScalingY":false,"lockRotation":true,"evented":true,"absolutePositioned":false,"perPixelTargetFind":false,"centeredScaling":false,"styles":{}}],"perPixelTargetFind":false,"centeredScaling":false}}